gcsstaff/__init__.py
gcsstaff/cli.py
gcsstaff-0.1.0.dist-info/METADATA
gcsstaff-0.1.0.dist-info/WHEEL
gcsstaff-0.1.0.dist-info/top_level.txt
gcsstaff-0.1.0.dist-info/RECORD
